jaredstef_headers/__init__.py
jaredstef_headers/_version.py
jaredstef_headers-1.0.1.data/data/share/jupyter/labextensions/@jaredstef/headers/package.json
jaredstef_headers-1.0.1.data/data/share/jupyter/labextensions/@jaredstef/headers/schemas/@jaredstef/headers/package.json.orig
jaredstef_headers-1.0.1.data/data/share/jupyter/labextensions/@jaredstef/headers/schemas/@jaredstef/headers/plugin.json
jaredstef_headers-1.0.1.data/data/share/jupyter/labextensions/@jaredstef/headers/static/509.d8b7dc02013d895c561a.js
jaredstef_headers-1.0.1.data/data/share/jupyter/labextensions/@jaredstef/headers/static/728.77c84375c0c1c5c88d72.js
jaredstef_headers-1.0.1.data/data/share/jupyter/labextensions/@jaredstef/headers/static/remoteEntry.bcebed26f005f9de7e0e.js
jaredstef_headers-1.0.1.data/data/share/jupyter/labextensions/@jaredstef/headers/static/style.js
jaredstef_headers-1.0.1.data/data/share/jupyter/labextensions/@jaredstef/headers/static/third-party-licenses.json
jaredstef_headers-1.0.1.data/data/share/jupyter/labextensions/@jaredstef/headers/install.json
jaredstef_headers-1.0.1.dist-info/METADATA
jaredstef_headers-1.0.1.dist-info/WHEEL
jaredstef_headers-1.0.1.dist-info/licenses/LICENSE
jaredstef_headers-1.0.1.dist-info/RECORD
