Metadata-Version: 2.3
Name: jaredstef_headers
Version: 1.0.1
Dynamic: Keywords
Summary: Customizable cell headers for Jupyter
Project-URL: Homepage, https://github.com/jaredstef/headers
Project-URL: Bug Tracker, https://github.com/jaredstef/headers/issues
Project-URL: Repository, https://github.com/jaredstef/headers.git
Author-email: Jared Stefanowicz <jaredstef@icloud.com>
License: BSD 3-Clause License
License-File: LICENSE
Classifier: Framework :: Jupyter
Classifier: Framework :: Jupyter :: JupyterLab
Classifier: Framework :: Jupyter :: JupyterLab :: 4
Classifier: Framework :: Jupyter :: JupyterLab :: Extensions
Classifier: Framework :: Jupyter :: JupyterLab :: Extensions :: Prebuilt
Classifier: License :: OSI Approved :: BSD License
Classifier: Programming Language :: Python
Classifier: Programming Language :: Python :: 3
Classifier: Programming Language :: Python :: 3.8
Classifier: Programming Language :: Python :: 3.9
Classifier: Programming Language :: Python :: 3.10
Classifier: Programming Language :: Python :: 3.11
Classifier: Programming Language :: Python :: 3.12
Requires-Python: >=3.8
